src/__init__.py
src/__main__.py
src/agent/__init__.py
src/agent/base.py
src/agent/speech.py
src/agent/zzzlistener.py
src/components/__init__.py
src/components/classifier.py
src/components/prompt.py
src/components/tool.py
src/context/__init__.py
src/context/base.py
src/context/member.py
src/context/messages.py
src/gui/__init__.py
src/gui/main.py
src/gui/style.py
src/gui/components/__init__.py
src/gui/components/agent_settings.py
src/gui/components/bubbles.py
src/gui/components/config.py
src/gui/components/group_settings.py
src/gui/pages/__init__.py
src/gui/pages/agents.py
src/gui/pages/chat.py
src/gui/pages/contexts.py
src/gui/pages/settings.py
src/gui/widgets/__init__.py
src/gui/widgets/base.py
src/gui/widgets/comboboxes.py
src/gui/widgets/content.py
src/operations/__init__.py
src/operations/action.py
src/operations/parameters.py
src/operations/react.py
src/operations/schedule.py
src/operations/task.py
src/operations/actions/Alarms.py
src/operations/actions/Assistant_Configuration.py
src/operations/actions/Audio_Playback.py
src/operations/actions/Clipboard_Operations.py
src/operations/actions/Desktop_Management.py
src/operations/actions/Desktop_Software_Apps.py
src/operations/actions/Email_OR_SMS_OR_Messaging.py
src/operations/actions/Files_and_Directories.py
src/operations/actions/Firestick.py
src/operations/actions/Image_And_Video_Production.py
src/operations/actions/Lists.py
src/operations/actions/Navigation.py
src/operations/actions/RemindersAndEvents.py
src/operations/actions/Video_Playback.py
src/operations/actions/Weather_Forecast.py
src/operations/actions/Web_Browser_and_Website.py
src/operations/actions/_Uncategorised.py
src/operations/actions/__init__.py
src/operations/actions/zzz/Projects.py
src/operations/actions/zzz/Software_OR_Website_Development_Actions.py
src/operations/actions/zzz/__init__.py
src/plugins/__init__.py
src/plugins/autogen/__init__.py
src/plugins/autogen/modules/__init__.py
src/plugins/autogen/modules/agent_plugin.py
agentpilot-0.2.0rc1.dist-info/LICENSE
agentpilot-0.2.0rc1.dist-info/METADATA
agentpilot-0.2.0rc1.dist-info/WHEEL
agentpilot-0.2.0rc1.dist-info/top_level.txt
agentpilot-0.2.0rc1.dist-info/RECORD
