Metadata-Version: 2.1
Name: agentpilot
Version: 0.2.0rc1
Summary: A cross-platform desktop app to create, manage, and chat with AI agents
Author: jbexta
Author-email: jbexta <agentpilotai@gmail.com>
License: GNU AFFERO GENERAL PUBLIC LICENSE
Project-URL: Homepage, https://github.com/jbexta/AgentPilot
Keywords: ai,agent,framework,conversational,llm,chatbot,ui
Requires-Python: >=3.10
License-File: LICENSE
